hdfs_lmdc/HDFSWrapperBase.py
hdfs_lmdc/HDFSWrapperJava.py
hdfs_lmdc/demo.py
hdfs_lmdc/hdfs.py
hdfs_lmdc-2.0.7.dist-info/LICENSE
hdfs_lmdc-2.0.7.dist-info/METADATA
hdfs_lmdc-2.0.7.dist-info/WHEEL
hdfs_lmdc-2.0.7.dist-info/entry_points.txt
hdfs_lmdc-2.0.7.dist-info/top_level.txt
hdfs_lmdc-2.0.7.dist-info/RECORD
