Metadata-Version: 2.1
Name: hdfs-lmdc
Version: 2.0.7
Summary: Esta biblioteca tem como objetivo generalizar funções da integração entre HDFS e Python utilizando HDFS3 ou JavaWrapper
Home-page: https://github.com/LMDC-UFF/hdfs-python
Author: LMDC-UFF
Author-email: opensource@lmdc.uff.br
License: MIT
Platform: UNKNOWN
Classifier: License :: OSI Approved :: MIT License
Classifier: Programming Language :: Python :: 3
Classifier: Programming Language :: Python :: 3.6
Classifier: Programming Language :: Python :: 3.7
Requires-Dist: hdfs3
Requires-Dist: pillow (==6.2.2)
